pydeidentify/__init__.py
pydeidentify/deid.py
pydeidentify-0.1.2.dist-info/WHEEL
pydeidentify-0.1.2.dist-info/METADATA
pydeidentify-0.1.2.dist-info/RECORD
