Metadata-Version: 2.1
Name: pydeidentify
Version: 0.1.2
Summary: A simple text deidentification tool, built on huggingface's named entity recognition pipeline
License: MIT
Author: Lucasc-99
Author-email: lucascecchi@gmail.com
Requires-Python: >=3.8,<4.0
Classifier: License :: OSI Approved :: MIT License
Classifier: Programming Language :: Python :: 3
Classifier: Programming Language :: Python :: 3.10
Classifier: Programming Language :: Python :: 3.8
Classifier: Programming Language :: Python :: 3.9
Requires-Dist: torch (>=1.12.0,<2.0.0)
Requires-Dist: transformers (>=4.20.1,<5.0.0)
